foGLEb/__init__.py
foGLEb-0.0.2.dist-info/LICENSE.txt
foGLEb-0.0.2.dist-info/METADATA
foGLEb-0.0.2.dist-info/WHEEL
foGLEb-0.0.2.dist-info/top_level.txt
foGLEb-0.0.2.dist-info/RECORD
