Metadata-Version: 2.1
Name: foGLEb
Version: 0.0.2
Summary: A library that makes pygame developement a more easier and beginner friendly process.
Home-page: 
Author: Adam Yang
Author-email: adam.fun.code@gmail.com
License: MIT
Keywords: foGLEb
Classifier: Development Status :: 5 - Production/Stable
Classifier: Intended Audience :: Education
Classifier: Operating System :: OS Independent
Classifier: License :: OSI Approved :: MIT License
Classifier: Programming Language :: Python :: 3
License-File: LICENSE.txt
Requires-Dist: pygame (>=2.6.0)
